falcon/__init__.py
falcon/config.py
falcon/falcon.py
falcon/cluster/__init__.py
falcon/cluster/cluster.py
falcon/cluster/spectrum.py
falcon/ms_io/__init__.py
falcon/ms_io/mgf_io.py
falcon/ms_io/ms_io.py
falcon/ms_io/mzml_io.py
falcon/ms_io/mzxml_io.py
falcon_ms-0.1.3.dist-info/LICENSE.txt
falcon_ms-0.1.3.dist-info/METADATA
falcon_ms-0.1.3.dist-info/WHEEL
falcon_ms-0.1.3.dist-info/entry_points.txt
falcon_ms-0.1.3.dist-info/top_level.txt
falcon_ms-0.1.3.dist-info/RECORD
