Metadata-Version: 2.1
Name: falcon-ms
Version: 0.1.3
Summary: Large-scale tandem mass spectrum clustering using fast nearest neighbor searching
Home-page: https://github.com/bittremieux/falcon
Author: Wout Bittremieux
Author-email: wbittremieux@health.ucsd.edu
License: BSD-3-Clause License
Project-URL: Bug Tracker, https://github.com/bittremieux/falcon/issues
Platform: UNKNOWN
Classifier: Intended Audience :: Science/Research
Classifier: License :: OSI Approved :: BSD License
Classifier: Operating System :: MacOS
Classifier: Operating System :: Unix
Classifier: Programming Language :: Python :: 3
Classifier: Topic :: Scientific/Engineering :: Bio-Informatics
Requires-Python: >=3.8
License-File: LICENSE.txt
Requires-Dist: configargparse (>=1.4)
Requires-Dist: faiss-cpu (>=1.6.5)
Requires-Dist: fastcluster (>=1.1.26)
Requires-Dist: joblib (>=1.0.0)
Requires-Dist: lxml (>=4.6.2)
Requires-Dist: natsort (>=7.1.0)
Requires-Dist: numba (>=0.52.0)
Requires-Dist: numpy (>=1.19.4)
Requires-Dist: pandas (>=1.2.0)
Requires-Dist: pyarrow (>=2.0.0)
Requires-Dist: pyteomics (>=4.4.0)
Requires-Dist: scikit-learn (>=0.24.0)
Requires-Dist: scipy (>=1.5.3)
Requires-Dist: spectrum-utils (>=0.3.5)
Requires-Dist: tqdm (>=4.55.0)
Provides-Extra: dev
Requires-Dist: flake8 ; extra == 'dev'
